qualitics/__init__.py
qualitics/Checks/__init__.py
qualitics/Checks/base.py
qualitics/Checks/check_runner.py
qualitics/Checks/custom_sql_check.py
qualitics/Checks/null_check.py
qualitics/Checks/pii_check.py
qualitics/Checks/row_count_check.py
qualitics/Checks/Freshness_Check/__init__.py
qualitics/Checks/Freshness_Check/freshness_check.py
qualitics/Checks/Freshness_Check/freshness_monitor.py
qualitics/CliCheckResult/__init__.py
qualitics/CliProfilerResult/__init__.py
qualitics/Config_parser/Test.py
qualitics/Config_parser/__init__.py
qualitics/Config_parser/configService.py
qualitics/Config_parser/dictHelper.py
qualitics/Config_parser/nestedKeyAccessor.py
qualitics/Connectors/__init__.py
qualitics/Connectors/base.py
qualitics/Connectors/connector_factory.py
qualitics/Connectors/credential_manager.py
qualitics/Connectors/rds_connector.py
qualitics/Connectors/redshift_connector.py
qualitics/Error/__init__.py
qualitics/Error/errorHandler.py
qualitics/Notification/__init__.py
qualitics/Notification/notification_service.py
qualitics/Profilers/__init__.py
qualitics/Profilers/base_profiler.py
qualitics/Profilers/column_profiler.py
qualitics/Profilers/database_profiler.py
qualitics/Profilers/profilingconfig.py
qualitics/Profilers/table_profiler.py
qualitics/Query_builder/PSQL_queries.py
qualitics/Query_builder/__init__.py
qualitics/Utils/__init__.py
qualitics/Utils/profile_store.py
qualitics/Utils/query_executor.py
qualitics/Utils/sql_helpers.py
qualitics/audit/__init__.py
qualitics/audit/results_auditing.py
qualitics/cli/__init__.py
qualitics/cli/dqtoolcli.py
qualitics/cli/render_check_html.py
qualitics/cli/render_profiling_html.py
qualitics/logger/__init__.py
qualitics/logger/custom_logs.py
qualitics-1.0.0.dist-info/METADATA
qualitics-1.0.0.dist-info/WHEEL
qualitics-1.0.0.dist-info/entry_points.txt
qualitics-1.0.0.dist-info/top_level.txt
qualitics-1.0.0.dist-info/RECORD
